base/__init__.py
base/__main__.py
base/application/__init__.py
base/application/components.py
base/application/service.py
base/application/api/__init__.py
base/application/api/user/__init__.py
base/application/api/user/change_password.py
base/application/api/user/faccess.py
base/application/api/user/forgot.py
base/application/api/user/gaccess.py
base/application/api/user/login.py
base/application/api/user/logout.py
base/application/api/user/register.py
base/application/api/utils/__init__.py
base/application/api/utils/hash2params.py
base/application/api/utils/mail_queue.py
base/application/api/utils/options.py
base/application/api_hooks/__init__.py
base/application/api_hooks/api_hooks.py
base/application/api_hooks/token_hooks.py
base/application/helpers/__init__.py
base/application/helpers/api_specification.py
base/application/helpers/exceptions.py
base/application/helpers/importer.py
base/application/helpers/tokenizer.py
base/application/lookup/__init__.py
base/application/lookup/authentication_level.py
base/application/lookup/authentication_type.py
base/application/lookup/database_types.py
base/application/lookup/exit_status.py
base/application/lookup/responses.py
base/application/lookup/session_storage.py
base/application/lookup/session_token_type.py
base/application/lookup/user_roles.py
base/application/templates/introduction.html
base/application/templates/specification.html
base/bin/__init__.py
base/bin/basemanager
base/bin/basemanager.py
base/builder/__init__.py
base/builder/project_maker.py
base/builder/maker/__init__.py
base/builder/maker/common.py
base/builder/maker/component_builder.py
base/builder/maker/database_builder.py
base/builder/maker/database_helpers.py
base/builder/maker/playground_builder.py
base/builder/maker/project_builder.py
base/builder/maker/components/__init__.py
base/builder/maker/components/blog_builder.py
base/builder/maker/components/site_builder.py
base/builder/playground/index.html
base/builder/playground/playground
dcbase-1.13.5.dist-info/LICENSE.txt
dcbase-1.13.5.dist-info/METADATA
dcbase-1.13.5.dist-info/WHEEL
dcbase-1.13.5.dist-info/top_level.txt
dcbase-1.13.5.dist-info/RECORD
