Metadata-Version: 2.1
Name: dcbase
Version: 1.13.5
Summary: Base, simple scaling project
Home-page: https://github.com/digital-cube/BASE
Author: Digital Cube doo
Author-email: info@digitalcube.rs
License: https://www.gnu.org/licenses/gpl-3.0.en.html
Platform: UNKNOWN
Requires-Dist: tornado
Requires-Dist: bcrypt
Requires-Dist: sendgrid
